loguetools/__init__.py
loguetools/common.py
loguetools/dump.py
loguetools/explode.py
loguetools/og.py
loguetools/prologue.py
loguetools/translate.py
loguetools/version.py
loguetools/xd.py
loguetools/tests/__init__.py
loguetools/tests/test_common.py
loguetools/tests/test_dump.py
loguetools/tests/test_explode.py
loguetools/tests/test_translate.py
loguetools-0.1.4.dist-info/LICENSE.txt
loguetools-0.1.4.dist-info/METADATA
loguetools-0.1.4.dist-info/WHEEL
loguetools-0.1.4.dist-info/entry_points.txt
loguetools-0.1.4.dist-info/top_level.txt
loguetools-0.1.4.dist-info/RECORD
