Metadata-Version: 2.1
Name: loguetools
Version: 0.1.4
Summary: Korg minilogue family patch manipulation tools
Home-page: https://github.com/gazzar/loguetools
Author: Gary Ruben
Author-email: gary.ruben@gmail.com
License: UNKNOWN
Platform: UNKNOWN
Classifier: Programming Language :: Python :: 3
Classifier: License :: OSI Approved :: BSD License
Classifier: Operating System :: OS Independent
Requires-Python: >=3.7
Requires-Dist: Click
